proxio/__init__.py
proxio/py.typed
proxio-0.0.3.dist-info/METADATA
proxio-0.0.3.dist-info/WHEEL
proxio-0.0.3.dist-info/entry_points.txt
proxio-0.0.3.dist-info/licenses/LICENSE
proxio-0.0.3.dist-info/RECORD
